pyprojectify/__init__.py
pyprojectify/cli.py
pyprojectify/pyprojectify.py
pyprojectify/utils.py
pyprojectify-0.3.1.dist-info/LICENSE
pyprojectify-0.3.1.dist-info/WHEEL
pyprojectify-0.3.1.dist-info/METADATA
pyprojectify-0.3.1.dist-info/RECORD
